README.md
setup.cfg
setup.py
DeepSecurity/APIKey.py
DeepSecurity/APIUsageMetrics.py
DeepSecurity/Administrators.py
DeepSecurity/AgentDeploymentScripts.py
DeepSecurity/AgentVersionControl.py
DeepSecurity/AwsConnectors.py
DeepSecurity/Certificates.py
DeepSecurity/ComputerGroups.py
DeepSecurity/Computers.py
DeepSecurity/Contacts.py
DeepSecurity/EventBasedTasks.py
DeepSecurity/IntegrityMonitoring.py
DeepSecurity/IntrusionPrevention.py
DeepSecurity/LogInspectionRules.py
DeepSecurity/Policies.py
DeepSecurity/ReportTemplates.py
DeepSecurity/ScheduledTasks.py
DeepSecurity/Scripts.py
DeepSecurity/SystemSettings.py
DeepSecurity/Tenants.py
DeepSecurity/__init__.py
DeepSecurity/__version__.py
DeepSecurity/antimalware.py
DeepSecurity/applicationControl.py
DeepSecurity/config.py
DeepSecurity/connect.py
DeepSecurity/firewall.py
DeepSecurity/gcpconnector.py
ds_sdk_mini.egg-info/PKG-INFO
ds_sdk_mini.egg-info/SOURCES.txt
ds_sdk_mini.egg-info/dependency_links.txt
ds_sdk_mini.egg-info/requires.txt
ds_sdk_mini.egg-info/top_level.txt