Metadata-Version: 2.1
Name: ds-sdk-mini
Version: 0.0.9
Summary: A lightweight SDK for Trend Micro Deep Security
Home-page: https://github.com/johnsobm/ds-sdk-mini
Author: Brendan Johnson
Author-email: brendan.johnson@gmail.com
License: UNKNOWN
Platform: UNKNOWN
Classifier: Intended Audience :: Developers
Classifier: Natural Language :: English
Classifier: License :: OSI Approved :: MIT License
Classifier: Programming Language :: Python
Classifier: Programming Language :: Python :: 3.6
Classifier: Programming Language :: Python :: 3.7
Classifier: Programming Language :: Python :: 3.8
Requires-Python: >=3.6
